{
  "item-states": [
    {
      "folded": true,
      "id": "130a9bdA5pJb7sMTmjozHCS"
    },
    {
      "folded": true,
      "id": "32575YpdOdBVYOd8RN+WODz"
    },
    {
      "folded": true,
      "id": "52fbeYN82tDiovgeSpvjhmP"
    },
    {
      "folded": true,
      "id": "1663cdK3FZPy7KhJu8OZm0J"
    },
    {
      "folded": true,
      "id": "e21c1oJkD5B27o7O9u3Yfmc"
    },
    {
      "folded": true,
      "id": "d0588PRs8xFMrUlxEQEVcXw"
    },
    {
      "folded": true,
      "id": "32d8aaaFqZFVp6e9VVnTzB0"
    }
  ]
}